[
    {
        "username": "surya.sonti",
        "password": "hello"
    },
    {
        "username": "srikanth.maringanti",
        "password": "hello"
    },
    {
        "username": "praveen.ogirala",
        "password": "hello"
    },
    {
        "username": "dd",
        "password": "dd"
    },
    {
        "username": "kol",
        "password": "kol"
    },
    {
        "username": "hello",
        "password": "hello"
    },
    {
        "username": "surya",
        "password": "lpplp"
    },
    {
        "username": "hello",
        "password": "hello"
    },
    {
        "username": "jik",
        "password": "kij"
    },
    {
        "username": "jik",
        "password": "kij"
    },
    {
        "username": "jik",
        "password": "kij"
    },
    {
        "username": "jik",
        "password": "kij"
    },
    {
        "username": "abac",
        "password": "abac"
    },
    {
        "username": "sravya",
        "password": "sravya"
    },
    {
        "username": "sravya",
        "password": "sravya"
    },
    {
        "username": "sravya",
        "password": "sravya"
    },
    {
        "username": "sravya",
        "password": "sravya"
    },
    {
        "username": "sravya",
        "password": "sravya"
    },
    {
        "username": "Sravya",
        "password": "sravya"
    },
    {
        "username": "srav",
        "password": "srav"
    },
    {
        "username": "srav",
        "password": "srav"
    },
    {
        "username": "suryateja",
        "password": "suryateja"
    },
    {
        "username": "suryat",
        "password": "suryat"
    }
]